pyfibaro/__init__.py
pyfibaro/fibaro_client.py
pyfibaro/fibaro_data_helper.py
pyfibaro/fibaro_device.py
pyfibaro/fibaro_device_manager.py
pyfibaro/fibaro_info.py
pyfibaro/fibaro_login.py
pyfibaro/fibaro_room.py
pyfibaro/fibaro_scene.py
pyfibaro/fibaro_state_handler.py
pyfibaro/fibaro_state_multiplexer.py
pyfibaro/fibaro_state_resolver.py
pyfibaro/common/__init__.py
pyfibaro/common/const.py
pyfibaro/common/rest_client.py
pyfibaro-0.8.2.dist-info/LICENSE
pyfibaro-0.8.2.dist-info/METADATA
pyfibaro-0.8.2.dist-info/WHEEL
pyfibaro-0.8.2.dist-info/top_level.txt
pyfibaro-0.8.2.dist-info/RECORD
