Metadata-Version: 2.2
Name: pyfibaro
Version: 0.8.2
Summary: Simple API to access fibaro home center from any Python 3 script. Designed for Home Assistant (but not only)
Home-page: https://github.com/rappenze/pyfibaro
Author: Roman Appenzeller
Author-email: 
License: MIT
Classifier: License :: OSI Approved :: MIT License
Classifier: Programming Language :: Python :: 3
Classifier: Programming Language :: Python :: 3 :: Only
Classifier: Programming Language :: Python :: 3.11
Classifier: Programming Language :: Python :: 3.12
Classifier: Programming Language :: Python :: 3.13
Classifier: Programming Language :: Python :: Implementation :: CPython
Classifier: Programming Language :: Python :: Implementation :: PyPy
Classifier: Topic :: Home Automation
Requires-Python: >=3.11
License-File: LICENSE
Requires-Dist: requests~=2.32
